ghidra_pipe/__init__.py
ghidra_pipe/pipe_client.py
ghidra_pipe/pipe_default_conf.py
ghidra_pipe/pipe_server.py
ghidra_pipe/plugin_ghidra_pipe_server_start.py
ghidra_pipe/plugin_ghidra_pipe_server_stop.py
scripts/__init__.py
scripts/ghidra_pipe.py
ghidra_pipe-1.0.5.dist-info/COPYING
ghidra_pipe-1.0.5.dist-info/METADATA
ghidra_pipe-1.0.5.dist-info/NOTICE
ghidra_pipe-1.0.5.dist-info/WHEEL
ghidra_pipe-1.0.5.dist-info/entry_points.txt
ghidra_pipe-1.0.5.dist-info/top_level.txt
ghidra_pipe-1.0.5.dist-info/RECORD
