Metadata-Version: 2.1
Name: ghidra-pipe
Version: 1.0.5
Summary: ghidra-pipe: Teleport Python code from CPython to Jython
Home-page: https://github.com/vincentdary/ghidra-pipe
Author: Vincent Dary
Author-email: 
Project-URL: Bug Tracker, https://github.com/vincentdary/ghidra-pipe/issues
Classifier: Programming Language :: Python :: 3
Classifier: Operating System :: POSIX :: Linux
Classifier: Operating System :: Microsoft :: Windows
Classifier: License :: OSI Approved :: GNU General Public License v3 (GPLv3)
Requires-Python: >=3.5.0
License-File: COPYING
License-File: NOTICE
Provides-Extra: dev
Requires-Dist: psutil ; extra == 'dev'
Requires-Dist: pytest ; extra == 'dev'
Requires-Dist: pytest-cov ; extra == 'dev'
Requires-Dist: pytest-order ; extra == 'dev'
